odoo/addons/web_widget_dropdown_dynamic/README.rst
odoo/addons/web_widget_dropdown_dynamic/__init__.py
odoo/addons/web_widget_dropdown_dynamic/__manifest__.py
odoo/addons/web_widget_dropdown_dynamic/i18n/ca.po
odoo/addons/web_widget_dropdown_dynamic/i18n/es.po
odoo/addons/web_widget_dropdown_dynamic/i18n/es_ES.po
odoo/addons/web_widget_dropdown_dynamic/i18n/fr.po
odoo/addons/web_widget_dropdown_dynamic/i18n/pt_BR.po
odoo/addons/web_widget_dropdown_dynamic/i18n/sk.po
odoo/addons/web_widget_dropdown_dynamic/i18n/web_widget_dropdown_dynamic.pot
odoo/addons/web_widget_dropdown_dynamic/readme/CONTRIBUTORS.rst
odoo/addons/web_widget_dropdown_dynamic/readme/DESCRIPTION.rst
odoo/addons/web_widget_dropdown_dynamic/readme/ROADMAP.rst
odoo/addons/web_widget_dropdown_dynamic/readme/USAGE.rst
odoo/addons/web_widget_dropdown_dynamic/static/description/icon.png
odoo/addons/web_widget_dropdown_dynamic/static/description/index.html
odoo/addons/web_widget_dropdown_dynamic/static/src/js/basic_model.js
odoo/addons/web_widget_dropdown_dynamic/static/src/js/field_dynamic_dropdown.js
odoo/addons/web_widget_dropdown_dynamic/static/tests/web_widget_dropdown_dynamic_tests.js
odoo/addons/web_widget_dropdown_dynamic/templates/assets.xml
odoo12_addon_web_widget_dropdown_dynamic-12.0.1.0.1.dist-info/METADATA
odoo12_addon_web_widget_dropdown_dynamic-12.0.1.0.1.dist-info/WHEEL
odoo12_addon_web_widget_dropdown_dynamic-12.0.1.0.1.dist-info/top_level.txt
odoo12_addon_web_widget_dropdown_dynamic-12.0.1.0.1.dist-info/RECORD
